{"type_functionality":0,"model":{"text":"{\"0\": {\"question\": [{\"params\": {\"tag\": \"\", \"text\": \"Estamos validando la imagen, aguarde unos instantes por favor!\", \"type\": \"external\", \"on_error\": null, \"recipient\": {\"type\": \"all_contacts\", \"way_of_communication\": \"over_all\"}, \"is_in_starting_block\": true, \"send_to_all_chat_sources\": true}, \"handler\": \"send_message\"}], \"block_uuid\": \"07bdea08-38e0-45ac-bb28-605541c02c0f\"}, \"conversation\": false}","name":"REVISAR_IMAGE","positions":"[{\"x\": 0, \"y\": 0, \"z\": 2, \"id\": 0, \"goto\": {\"block\": 4}, \"step\": -1, \"type\": \"start\", \"width\": 170, \"height\": 38, \"actions\": [{\"id\": -3, \"sort\": 0, \"links\": [], \"params\": {\"params\": [], \"handler\": \"_start\"}}], \"deletable\": true}, {\"x\": -350, \"y\": 0, \"z\": 6, \"id\": -1, \"code\": \"trigger\", \"step\": -1, \"type\": \"static\", \"width\": 260, \"height\": 0, \"actions\": [], \"deletable\": true}, {\"x\": 460, \"y\": 0, \"z\": 23, \"id\": 4, \"goto\": null, \"name\": \"Mensaje\", \"step\": 0, \"type\": \"question\", \"width\": 400, \"height\": 170, \"actions\": [{\"id\": 121, \"sort\": 0, \"links\": [], \"params\": {\"params\": {\"tag\": \"\", \"text\": \"Estamos validando la imagen, aguarde unos instantes por favor!\", \"type\": \"external\", \"recipient\": {\"type\": \"all_contacts\", \"way_of_communication\": \"over_all\"}, \"is_in_starting_block\": true, \"send_to_all_chat_sources\": true}, \"handler\": \"send_message\"}}], \"deletable\": true, \"block_uuid\": \"07bdea08-38e0-45ac-bb28-605541c02c0f\"}]","type":2}}